factorial_hl/__init__.py
factorial_hl/app.py
factorial_hl/factorial.py
factorial_hl-0.1.0.dist-info/METADATA
factorial_hl-0.1.0.dist-info/WHEEL
factorial_hl-0.1.0.dist-info/RECORD
